lollms_client/__init__.py
lollms_client/lollms_agentic.py
lollms_client/lollms_base_binding.py
lollms_client/lollms_bindings_utils.py
lollms_client/lollms_config.py
lollms_client/lollms_core.py
lollms_client/lollms_discussion.py
lollms_client/lollms_js_analyzer.py
lollms_client/lollms_llm_binding.py
lollms_client/lollms_mcp_binding.py
lollms_client/lollms_mcp_security.py
lollms_client/lollms_personality.py
lollms_client/lollms_python_analyzer.py
lollms_client/lollms_stt_binding.py
lollms_client/lollms_text_processing.py
lollms_client/lollms_tti_binding.py
lollms_client/lollms_ttm_binding.py
lollms_client/lollms_tts_binding.py
lollms_client/lollms_ttv_binding.py
lollms_client/lollms_types.py
lollms_client/lollms_utilities.py
lollms_client/assets/models_ctx_sizes.json
lollms_client/llm_bindings/__init__.py
lollms_client/llm_bindings/azure_openai/__init__.py
lollms_client/llm_bindings/claude/__init__.py
lollms_client/llm_bindings/gemini/__init__.py
lollms_client/llm_bindings/grok/__init__.py
lollms_client/llm_bindings/groq/__init__.py
lollms_client/llm_bindings/hugging_face_inference_api/__init__.py
lollms_client/llm_bindings/litellm/__init__.py
lollms_client/llm_bindings/llama_cpp_server/__init__.py
lollms_client/llm_bindings/lollms/__init__.py
lollms_client/llm_bindings/lollms_webui/__init__.py
lollms_client/llm_bindings/mistral/__init__.py
lollms_client/llm_bindings/novita_ai/__init__.py
lollms_client/llm_bindings/ollama/__init__.py
lollms_client/llm_bindings/open_router/__init__.py
lollms_client/llm_bindings/openai/__init__.py
lollms_client/llm_bindings/openllm/__init__.py
lollms_client/llm_bindings/openwebui/__init__.py
lollms_client/llm_bindings/perplexity/__init__.py
lollms_client/llm_bindings/tensor_rt/__init__.py
lollms_client/llm_bindings/transformers/__init__.py
lollms_client/llm_bindings/vllm/__init__.py
lollms_client/mcp_bindings/local_mcp/__init__.py
lollms_client/mcp_bindings/local_mcp/default_tools/file_writer/file_writer.py
lollms_client-1.11.2.dist-info/licenses/LICENSE
lollms_client-1.11.2.dist-info/METADATA
lollms_client-1.11.2.dist-info/WHEEL
lollms_client-1.11.2.dist-info/top_level.txt
lollms_client-1.11.2.dist-info/RECORD
