Metadata-Version: 2.4
Name: lollms_client
Version: 1.11.2
Summary: A client library for LoLLMs generate endpoint
Author-email: ParisNeo <parisneoai@gmail.com>
License:                                  Apache License
Project-URL: Homepage, https://github.com/ParisNeo/lollms_client
Classifier: Programming Language :: Python :: 3
Classifier: Programming Language :: Python :: 3.8
Classifier: Programming Language :: Python :: 3.9
Classifier: Programming Language :: Python :: 3.10
Classifier: Programming Language :: Python :: 3.11
Classifier: Programming Language :: Python :: 3.12
Classifier: License :: OSI Approved :: Apache Software License
Classifier: Operating System :: OS Independent
Classifier: Intended Audience :: Developers
Classifier: Intended Audience :: Science/Research
Requires-Python: >=3.7
License-File: LICENSE
Requires-Dist: httpx
Requires-Dist: requests
Requires-Dist: ascii-colors
Requires-Dist: pipmaster>=1.0.5
Requires-Dist: pyyaml
Requires-Dist: tiktoken
Requires-Dist: pydantic
Requires-Dist: numpy
Requires-Dist: pillow
Requires-Dist: sqlalchemy
Requires-Dist: jsonschema
Dynamic: license-file
